pybrain/__init__.py
pybrain/cli.py
pybrain/core/__init__.py
pybrain/core/ai.py
pybrain/core/analytics.py
pybrain/core/decision.py
pybrain/core/harmonizer.py
pybrain/core/knowledge.py
brainsait_pybrain-0.1.0.dist-info/METADATA
brainsait_pybrain-0.1.0.dist-info/WHEEL
brainsait_pybrain-0.1.0.dist-info/entry_points.txt
brainsait_pybrain-0.1.0.dist-info/top_level.txt
brainsait_pybrain-0.1.0.dist-info/RECORD
