Metadata-Version: 2.4
Name: brainsait-pybrain
Version: 0.1.0
Summary: Unified Healthcare Intelligence Platform - AI-powered healthcare data harmonization and decision support
Author-email: "Dr. Fadil" <fadil@brainsait.com>, BrainSAIT Team <team@brainsait.com>
Maintainer-email: BrainSAIT Healthcare Innovation Lab <healthcare@brainsait.com>
License: Apache-2.0
Project-URL: Homepage, https://github.com/brainsait/pybrain
Project-URL: Documentation, https://pybrain.readthedocs.io
Project-URL: Repository, https://github.com/brainsait/pybrain
Project-URL: Issues, https://github.com/brainsait/pybrain/issues
Project-URL: Changelog, https://github.com/brainsait/pybrain/blob/main/CHANGELOG.md
Keywords: healthcare,ai,fhir,clinical-nlp,medical-ai,health-informatics,interoperability,decision-support,federated-learning,healthcare-analytics
Classifier: Development Status :: 4 - Beta
Classifier: Intended Audience :: Healthcare Industry
Classifier: Topic :: Scientific/Engineering :: Medical Science Apps.
Classifier: Topic :: Scientific/Engineering :: Artificial Intelligence
Classifier: License :: OSI Approved :: Apache Software License
Classifier: Programming Language :: Python :: 3
Classifier: Programming Language :: Python :: 3.8
Classifier: Programming Language :: Python :: 3.9
Classifier: Programming Language :: Python :: 3.10
Classifier: Programming Language :: Python :: 3.11
Classifier: Programming Language :: Python :: 3.12
Classifier: Operating System :: OS Independent
Classifier: Framework :: FastAPI
Requires-Python: >=3.8
Requires-Dist: fhir.resources>=6.5.0
Requires-Dist: pandas>=1.5.0
Requires-Dist: numpy>=1.23.0
Requires-Dist: scikit-learn>=1.2.0
Requires-Dist: torch>=2.0.0
Requires-Dist: transformers>=4.30.0
Requires-Dist: spacy>=3.5.0
Requires-Dist: networkx>=3.0
Requires-Dist: pydantic>=2.0
Requires-Dist: httpx>=0.24.0
Requires-Dist: fastapi>=0.100.0
Requires-Dist: uvicorn>=0.22.0
Requires-Dist: redis>=4.5.0
Requires-Dist: sqlalchemy>=2.0
Requires-Dist: alembic>=1.11.0
Requires-Dist: cryptography>=41.0.0
Requires-Dist: python-jose[cryptography]>=3.3.0
Requires-Dist: prometheus-client>=0.17.0
Requires-Dist: opentelemetry-api>=1.18.0
Requires-Dist: opentelemetry-sdk>=1.18.0
Requires-Dist: python-multipart>=0.0.6
Requires-Dist: aiofiles>=23.1.0
Requires-Dist: orjson>=3.9.0
Requires-Dist: python-dateutil>=2.8.2
Requires-Dist: pytz>=2023.3
Requires-Dist: langchain>=0.0.200
Requires-Dist: chromadb>=0.4.0
Requires-Dist: sentence-transformers>=2.2.2
Provides-Extra: dev
Requires-Dist: pytest>=7.3.0; extra == "dev"
Requires-Dist: pytest-asyncio>=0.21.0; extra == "dev"
Requires-Dist: pytest-cov>=4.1.0; extra == "dev"
Requires-Dist: black>=23.3.0; extra == "dev"
Requires-Dist: flake8>=6.0.0; extra == "dev"
Requires-Dist: mypy>=1.3.0; extra == "dev"
Requires-Dist: isort>=5.12.0; extra == "dev"
Requires-Dist: pre-commit>=3.3.0; extra == "dev"
Requires-Dist: pytest-mock>=3.11.0; extra == "dev"
Requires-Dist: factory-boy>=3.2.1; extra == "dev"
Requires-Dist: faker>=18.11.0; extra == "dev"
Requires-Dist: responses>=0.23.0; extra == "dev"
Provides-Extra: docs
Requires-Dist: sphinx>=7.0.0; extra == "docs"
Requires-Dist: sphinx-rtd-theme>=1.2.0; extra == "docs"
Requires-Dist: sphinx-autodoc-typehints>=1.23.0; extra == "docs"
Requires-Dist: myst-parser>=2.0.0; extra == "docs"
Provides-Extra: ml
Requires-Dist: tensorflow>=2.13.0; extra == "ml"
Requires-Dist: xgboost>=1.7.0; extra == "ml"
Requires-Dist: lightgbm>=3.3.0; extra == "ml"
Requires-Dist: optuna>=3.2.0; extra == "ml"
Requires-Dist: mlflow>=2.4.0; extra == "ml"
Provides-Extra: nlp
Requires-Dist: scispacy>=0.5.2; extra == "nlp"
Requires-Dist: medspacy>=1.0.0; extra == "nlp"
Requires-Dist: nltk>=3.8.0; extra == "nlp"
Requires-Dist: gensim>=4.3.0; extra == "nlp"
Provides-Extra: cloud
Requires-Dist: boto3>=1.26.0; extra == "cloud"
Requires-Dist: azure-storage-blob>=12.16.0; extra == "cloud"
Requires-Dist: google-cloud-storage>=2.9.0; extra == "cloud"
